Workbook

Sheet Como usar
B2: PLACAR DOS CHEFÕES
B3: Bônus 1 do ebook "Chefões do cartão" · Din no Chão
B5: DIN | C5: Oi, eu sou o Din. Esta planilha é o seu placar. Você coloca os chefões, ela mostra quem está batendo mais forte, qual atacar primeiro e se a barra de vida está caindo. Leva 10 minutos.
B7: COMO JOGAR
B8: 1 | C8: Apague o exemplo da Ana. As linhas escritas "EXEMPLO" são da Ana, a personagem do livro. Selecione os campos claros com borda e aperte Delete. As fórmulas ficam.
B9: 2 | C9: Monte a ficha dos seus chefões. Na aba "Meus chefões": nome, tipo (lista), vida (quanto deve hoje) e o mínimo ou a parcela. A taxa ao mês aparece sozinha. Sabe a do seu contrato? Digite em "Minha taxa".
B10: 3 | C10: Diga quanto sobra. No topo de "Meus chefões": quanto sobra por mês para as dívidas, depois do essencial. Essencial vem antes de qualquer chefão.
B11: 4 | C11: Escolha a estratégia. A planilha monta a ordem de ataque da Avalanche e da Bola de Neve. O primeiro da lista é o ALVO: ele recebe toda a sobra.
B12: 5 | C12: Marque o placar todo mês. Na aba "Placar mensal", anote o que pagou e a vida que ficou em cada chefão. O gráfico mostra a vida total caindo.
B13: 6 | C13: Siga o plano de 90 dias. Uma missão por semana. Marque "Feito" quando terminar.
B15: AS 3 REGRAS DO JOGO
B16: 1 | C16: Pague o essencial primeiro: comida, moradia, contas, remédio e transporte.
B17: 2 | C17: Pague o mínimo de todas as dívidas, para nenhuma atrasar.
B18: 3 | C18: Todo dinheiro que sobrar vai inteiro para UM chefão de cada vez: o ALVO.
B20: O QUE CADA COR QUER DIZER
C21: Campo claro com borda: é seu, preencha.
C22: Fundo verde-sálvia: fórmula. Não precisa mexer.
C23: Vermelho: o chefão está crescendo. O mínimo não cobre o ataque dele.
C24: Amarelo: o ALVO, quem recebe a sobra.
C25: Verde: chefão perdendo vida, ou fase vencida.
B27: A CONTA MAIS IMPORTANTE
B28: Ataque do mês = vida × taxa ao mês. Se o seu pagamento é menor que o ataque, a vida do chefão sobe: você está pagando e perdendo.
B30: BOM SABER
B31: • | C31: Taxa: digite 6,42% ou 0,0642. Se digitar 6,42 (sem o %), a planilha entende 6,42% ao mês.
B32: • | C32: Onde achar os números: Registrato do Banco Central (gov.br), fatura do cartão, app do banco e Serasa.
B33: • | C33: As fórmulas estão protegidas, sem senha, só para não apagar sem querer. Para mexer: Revisão > Desproteger planilha (Excel) ou Dados > Proteger páginas e intervalos (Google Planilhas).
B34: • | C34: No Google Planilhas: Arquivo > Importar > Fazer upload, ou abra o arquivo pelo Google Drive e use "Abrir com Planilhas Google".
B35: • | C35: A planilha não prevê a data de quitação: o mínimo do cartão muda a cada fatura. Para ver a batalha completa mês a mês, use o simulador do livro.
B37: Educativo: não é recomendação de investimento, não promete resultado e não substitui orientação profissional. Taxas médias do Banco Central de setembro de 2026 (consignado CLT: média de agosto de 2026). Confira sempre o contrato e o CET da sua dívida.

Sheet Meus chefões
A1: MEUS CHEFÕES
A2: Din: ninguém vence o que não enxerga. Quatro números por dívida e você sabe contra o que está lutando.
A4: Quanto sobra por mês para as dívidas (depois do essencial)? | E4: 600 | F4: ← EXEMPLO da Ana. Troque pelo seu valor.
A6: VIDA TOTAL | D6: ATAQUE DO MÊS | F6: MÍNIMOS SOMADOS | I6: SOBRA PARA O ALVO | K6: DANO REAL NO MÊS | M6: CRESCENDO
A7: =SUM(E11:E20) | D7: =SUM(J11:J20) | F7: =SUM(I11:I20) | I7: =IF(E4="","",E4-F7) | K7: =IF(E4="","",E4-D7) | M7: =COUNTIF(L11:L20,"CRESCENDO*")
A8: o que você deve hoje | D8: juros de 1 mês (vida × taxa) | F8: para nenhuma atrasar | I8: vai inteira para UM chefão | K8: o que pagar − o ataque do mês | M8: mínimo menor que o ataque
I9: =IF(E4="","",IF(E4<F7,"Não cobre nem os mínimos: veja a Fase 4 do livro (renegociar, trocar de dívida).",""))
A10: # | B10: Nome da dívida (onde está) | C10: Tipo (escolha na lista) | D10: Chefão | E10: Vida (R$) saldo devedor | F10: Taxa sugerida | G10: Minha taxa (opcional) | H10: Taxa usada | I10: Mínimo ou parcela (R$) | J10: Ataque do mês (vida × taxa) | K10: Dano do mínimo (mín. − ataque) | L10: Situação | M10: Ordem Avalanche | N10: Ordem Bola de Neve
A11: 1 | B11: EXEMPLO · Cartão do banco | C11: Parcelamento da fatura | D11: =IF(C11="","",IFERROR(INDEX(Taxas!$B$5:$B$13,MATCH(C11,Taxas!$A$5:$A$13,0)),"")) | E11: 2000 | F11: =IF(C11="","",IFERROR(IF(INDEX(Taxas!$D$5:$D$13,MATCH(C11,Taxas!$A$5:$A$13,0))="","",INDEX(Taxas!$D$5:$D$13,MATCH(C11,Taxas!$A$5:$A$13,0))),"")) | H11: =IF(ISNUMBER(G11),IF(G11>1,G11/100,G11),F11) | I11: 100 | J11: =IF(AND(ISNUMBER(E11),E11>0,ISNUMBER(H11)),E11*H11,"") | K11: =IF(AND(ISNUMBER(J11),ISNUMBER(I11)),I11-J11,"") | L11: =IF(NOT(ISNUMBER(E11)),"",IF(E11<=0,"FASE VENCIDA",IF(NOT(ISNUMBER(H11)),"Falta a taxa",IF(NOT(ISNUMBER(I11)),"Falta o mínimo",IF(ROUND(I11,2)<ROUND(J11,2),"CRESCENDO: o mínimo não cobre o ataque",IF(ROUND(I11,2)=ROUND(J11,2),"Parado: o mínimo só paga os juros","Perdendo vida")))))) | M11: =IF(AND(ISNUMBER(E11),E11>0,ISNUMBER(H11)),1+SUMPRODUCT(ISNUMBER($E$11:$E$20)*($E$11:$E$20>0)*ISNUMBER($H$11:$H$20)*($H$11:$H$20>H11))+SUMPRODUCT(ISNUMBER($E$11:$E$20)*($E$11:$E$20>0)*ISNUMBER($H$11:$H$20)*($H$11:$H$20=H11)*(ROW($H$11:$H$20)<ROW(H11))),"") | N11: =IF(AND(ISNUMBER(E11),E11>0,ISNUMBER(H11)),1+SUMPRODUCT(ISNUMBER($E$11:$E$20)*($E$11:$E$20>0)*ISNUMBER($H$11:$H$20)*($E$11:$E$20<E11))+SUMPRODUCT(ISNUMBER($E$11:$E$20)*($E$11:$E$20>0)*ISNUMBER($H$11:$H$20)*($E$11:$E$20=E11)*(ROW($E$11:$E$20)<ROW(E11))),"")
A12: 2 | B12: EXEMPLO · Cheque especial | C12: Cheque especial | D12: =IF(C12="","",IFERROR(INDEX(Taxas!$B$5:$B$13,MATCH(C12,Taxas!$A$5:$A$13,0)),"")) | E12: 800 | F12: =IF(C12="","",IFERROR(IF(INDEX(Taxas!$D$5:$D$13,MATCH(C12,Taxas!$A$5:$A$13,0))="","",INDEX(Taxas!$D$5:$D$13,MATCH(C12,Taxas!$A$5:$A$13,0))),"")) | H12: =IF(ISNUMBER(G12),IF(G12>1,G12/100,G12),F12) | I12: 50 | J12: =IF(AND(ISNUMBER(E12),E12>0,ISNUMBER(H12)),E12*H12,"") | K12: =IF(AND(ISNUMBER(J12),ISNUMBER(I12)),I12-J12,"") | L12: =IF(NOT(ISNUMBER(E12)),"",IF(E12<=0,"FASE VENCIDA",IF(NOT(ISNUMBER(H12)),"Falta a taxa",IF(NOT(ISNUMBER(I12)),"Falta o mínimo",IF(ROUND(I12,2)<ROUND(J12,2),"CRESCENDO: o mínimo não cobre o ataque",IF(ROUND(I12,2)=ROUND(J12,2),"Parado: o mínimo só paga os juros","Perdendo vida")))))) | M12: =IF(AND(ISNUMBER(E12),E12>0,ISNUMBER(H12)),1+SUMPRODUCT(ISNUMBER($E$11:$E$20)*($E$11:$E$20>0)*ISNUMBER($H$11:$H$20)*($H$11:$H$20>H12))+SUMPRODUCT(ISNUMBER($E$11:$E$20)*($E$11:$E$20>0)*ISNUMBER($H$11:$H$20)*($H$11:$H$20=H12)*(ROW($H$11:$H$20)<ROW(H12))),"") | N12: =IF(AND(ISNUMBER(E12),E12>0,ISNUMBER(H12)),1+SUMPRODUCT(ISNUMBER($E$11:$E$20)*($E$11:$E$20>0)*ISNUMBER($H$11:$H$20)*($E$11:$E$20<E12))+SUMPRODUCT(ISNUMBER($E$11:$E$20)*($E$11:$E$20>0)*ISNUMBER($H$11:$H$20)*($E$11:$E$20=E12)*(ROW($E$11:$E$20)<ROW(E12))),"")
A13: 3 | B13: EXEMPLO · Empréstimo do app | C13: Crédito pessoal | D13: =IF(C13="","",IFERROR(INDEX(Taxas!$B$5:$B$13,MATCH(C13,Taxas!$A$5:$A$13,0)),"")) | E13: 3000 | F13: =IF(C13="","",IFERROR(IF(INDEX(Taxas!$D$5:$D$13,MATCH(C13,Taxas!$A$5:$A$13,0))="","",INDEX(Taxas!$D$5:$D$13,MATCH(C13,Taxas!$A$5:$A$13,0))),"")) | H13: =IF(ISNUMBER(G13),IF(G13>1,G13/100,G13),F13) | I13: 150 | J13: =IF(AND(ISNUMBER(E13),E13>0,ISNUMBER(H13)),E13*H13,"") | K13: =IF(AND(ISNUMBER(J13),ISNUMBER(I13)),I13-J13,"") | L13: =IF(NOT(ISNUMBER(E13)),"",IF(E13<=0,"FASE VENCIDA",IF(NOT(ISNUMBER(H13)),"Falta a taxa",IF(NOT(ISNUMBER(I13)),"Falta o mínimo",IF(ROUND(I13,2)<ROUND(J13,2),"CRESCENDO: o mínimo não cobre o ataque",IF(ROUND(I13,2)=ROUND(J13,2),"Parado: o mínimo só paga os juros","Perdendo vida")))))) | M13: =IF(AND(ISNUMBER(E13),E13>0,ISNUMBER(H13)),1+SUMPRODUCT(ISNUMBER($E$11:$E$20)*($E$11:$E$20>0)*ISNUMBER($H$11:$H$20)*($H$11:$H$20>H13))+SUMPRODUCT(ISNUMBER($E$11:$E$20)*($E$11:$E$20>0)*ISNUMBER($H$11:$H$20)*($H$11:$H$20=H13)*(ROW($H$11:$H$20)<ROW(H13))),"") | N13: =IF(AND(ISNUMBER(E13),E13>0,ISNUMBER(H13)),1+SUMPRODUCT(ISNUMBER($E$11:$E$20)*($E$11:$E$20>0)*ISNUMBER($H$11:$H$20)*($E$11:$E$20<E13))+SUMPRODUCT(ISNUMBER($E$11:$E$20)*($E$11:$E$20>0)*ISNUMBER($H$11:$H$20)*($E$11:$E$20=E13)*(ROW($E$11:$E$20)<ROW(E13))),"")
A14: 4 | D14: =IF(C14="","",IFERROR(INDEX(Taxas!$B$5:$B$13,MATCH(C14,Taxas!$A$5:$A$13,0)),"")) | F14: =IF(C14="","",IFERROR(IF(INDEX(Taxas!$D$5:$D$13,MATCH(C14,Taxas!$A$5:$A$13,0))="","",INDEX(Taxas!$D$5:$D$13,MATCH(C14,Taxas!$A$5:$A$13,0))),"")) | H14: =IF(ISNUMBER(G14),IF(G14>1,G14/100,G14),F14) | J14: =IF(AND(ISNUMBER(E14),E14>0,ISNUMBER(H14)),E14*H14,"") | K14: =IF(AND(ISNUMBER(J14),ISNUMBER(I14)),I14-J14,"") | L14: =IF(NOT(ISNUMBER(E14)),"",IF(E14<=0,"FASE VENCIDA",IF(NOT(ISNUMBER(H14)),"Falta a taxa",IF(NOT(ISNUMBER(I14)),"Falta o mínimo",IF(ROUND(I14,2)<ROUND(J14,2),"CRESCENDO: o mínimo não cobre o ataque",IF(ROUND(I14,2)=ROUND(J14,2),"Parado: o mínimo só paga os juros","Perdendo vida")))))) | M14: =IF(AND(ISNUMBER(E14),E14>0,ISNUMBER(H14)),1+SUMPRODUCT(ISNUMBER($E$11:$E$20)*($E$11:$E$20>0)*ISNUMBER($H$11:$H$20)*($H$11:$H$20>H14))+SUMPRODUCT(ISNUMBER($E$11:$E$20)*($E$11:$E$20>0)*ISNUMBER($H$11:$H$20)*($H$11:$H$20=H14)*(ROW($H$11:$H$20)<ROW(H14))),"") | N14: =IF(AND(ISNUMBER(E14),E14>0,ISNUMBER(H14)),1+SUMPRODUCT(ISNUMBER($E$11:$E$20)*($E$11:$E$20>0)*ISNUMBER($H$11:$H$20)*($E$11:$E$20<E14))+SUMPRODUCT(ISNUMBER($E$11:$E$20)*($E$11:$E$20>0)*ISNUMBER($H$11:$H$20)*($E$11:$E$20=E14)*(ROW($E$11:$E$20)<ROW(E14))),"")
A15: 5 | D15: =IF(C15="","",IFERROR(INDEX(Taxas!$B$5:$B$13,MATCH(C15,Taxas!$A$5:$A$13,0)),"")) | F15: =IF(C15="","",IFERROR(IF(INDEX(Taxas!$D$5:$D$13,MATCH(C15,Taxas!$A$5:$A$13,0))="","",INDEX(Taxas!$D$5:$D$13,MATCH(C15,Taxas!$A$5:$A$13,0))),"")) | H15: =IF(ISNUMBER(G15),IF(G15>1,G15/100,G15),F15) | J15: =IF(AND(ISNUMBER(E15),E15>0,ISNUMBER(H15)),E15*H15,"") | K15: =IF(AND(ISNUMBER(J15),ISNUMBER(I15)),I15-J15,"") | L15: =IF(NOT(ISNUMBER(E15)),"",IF(E15<=0,"FASE VENCIDA",IF(NOT(ISNUMBER(H15)),"Falta a taxa",IF(NOT(ISNUMBER(I15)),"Falta o mínimo",IF(ROUND(I15,2)<ROUND(J15,2),"CRESCENDO: o mínimo não cobre o ataque",IF(ROUND(I15,2)=ROUND(J15,2),"Parado: o mínimo só paga os juros","Perdendo vida")))))) | M15: =IF(AND(ISNUMBER(E15),E15>0,ISNUMBER(H15)),1+SUMPRODUCT(ISNUMBER($E$11:$E$20)*($E$11:$E$20>0)*ISNUMBER($H$11:$H$20)*($H$11:$H$20>H15))+SUMPRODUCT(ISNUMBER($E$11:$E$20)*($E$11:$E$20>0)*ISNUMBER($H$11:$H$20)*($H$11:$H$20=H15)*(ROW($H$11:$H$20)<ROW(H15))),"") | N15: =IF(AND(ISNUMBER(E15),E15>0,ISNUMBER(H15)),1+SUMPRODUCT(ISNUMBER($E$11:$E$20)*($E$11:$E$20>0)*ISNUMBER($H$11:$H$20)*($E$11:$E$20<E15))+SUMPRODUCT(ISNUMBER($E$11:$E$20)*($E$11:$E$20>0)*ISNUMBER($H$11:$H$20)*($E$11:$E$20=E15)*(ROW($E$11:$E$20)<ROW(E15))),"")
A16: 6 | D16: =IF(C16="","",IFERROR(INDEX(Taxas!$B$5:$B$13,MATCH(C16,Taxas!$A$5:$A$13,0)),"")) | F16: =IF(C16="","",IFERROR(IF(INDEX(Taxas!$D$5:$D$13,MATCH(C16,Taxas!$A$5:$A$13,0))="","",INDEX(Taxas!$D$5:$D$13,MATCH(C16,Taxas!$A$5:$A$13,0))),"")) | H16: =IF(ISNUMBER(G16),IF(G16>1,G16/100,G16),F16) | J16: =IF(AND(ISNUMBER(E16),E16>0,ISNUMBER(H16)),E16*H16,"") | K16: =IF(AND(ISNUMBER(J16),ISNUMBER(I16)),I16-J16,"") | L16: =IF(NOT(ISNUMBER(E16)),"",IF(E16<=0,"FASE VENCIDA",IF(NOT(ISNUMBER(H16)),"Falta a taxa",IF(NOT(ISNUMBER(I16)),"Falta o mínimo",IF(ROUND(I16,2)<ROUND(J16,2),"CRESCENDO: o mínimo não cobre o ataque",IF(ROUND(I16,2)=ROUND(J16,2),"Parado: o mínimo só paga os juros","Perdendo vida")))))) | M16: =IF(AND(ISNUMBER(E16),E16>0,ISNUMBER(H16)),1+SUMPRODUCT(ISNUMBER($E$11:$E$20)*($E$11:$E$20>0)*ISNUMBER($H$11:$H$20)*($H$11:$H$20>H16))+SUMPRODUCT(ISNUMBER($E$11:$E$20)*($E$11:$E$20>0)*ISNUMBER($H$11:$H$20)*($H$11:$H$20=H16)*(ROW($H$11:$H$20)<ROW(H16))),"") | N16: =IF(AND(ISNUMBER(E16),E16>0,ISNUMBER(H16)),1+SUMPRODUCT(ISNUMBER($E$11:$E$20)*($E$11:$E$20>0)*ISNUMBER($H$11:$H$20)*($E$11:$E$20<E16))+SUMPRODUCT(ISNUMBER($E$11:$E$20)*($E$11:$E$20>0)*ISNUMBER($H$11:$H$20)*($E$11:$E$20=E16)*(ROW($E$11:$E$20)<ROW(E16))),"")
A17: 7 | D17: =IF(C17="","",IFERROR(INDEX(Taxas!$B$5:$B$13,MATCH(C17,Taxas!$A$5:$A$13,0)),"")) | F17: =IF(C17="","",IFERROR(IF(INDEX(Taxas!$D$5:$D$13,MATCH(C17,Taxas!$A$5:$A$13,0))="","",INDEX(Taxas!$D$5:$D$13,MATCH(C17,Taxas!$A$5:$A$13,0))),"")) | H17: =IF(ISNUMBER(G17),IF(G17>1,G17/100,G17),F17) | J17: =IF(AND(ISNUMBER(E17),E17>0,ISNUMBER(H17)),E17*H17,"") | K17: =IF(AND(ISNUMBER(J17),ISNUMBER(I17)),I17-J17,"") | L17: =IF(NOT(ISNUMBER(E17)),"",IF(E17<=0,"FASE VENCIDA",IF(NOT(ISNUMBER(H17)),"Falta a taxa",IF(NOT(ISNUMBER(I17)),"Falta o mínimo",IF(ROUND(I17,2)<ROUND(J17,2),"CRESCENDO: o mínimo não cobre o ataque",IF(ROUND(I17,2)=ROUND(J17,2),"Parado: o mínimo só paga os juros","Perdendo vida")))))) | M17: =IF(AND(ISNUMBER(E17),E17>0,ISNUMBER(H17)),1+SUMPRODUCT(ISNUMBER($E$11:$E$20)*($E$11:$E$20>0)*ISNUMBER($H$11:$H$20)*($H$11:$H$20>H17))+SUMPRODUCT(ISNUMBER($E$11:$E$20)*($E$11:$E$20>0)*ISNUMBER($H$11:$H$20)*($H$11:$H$20=H17)*(ROW($H$11:$H$20)<ROW(H17))),"") | N17: =IF(AND(ISNUMBER(E17),E17>0,ISNUMBER(H17)),1+SUMPRODUCT(ISNUMBER($E$11:$E$20)*($E$11:$E$20>0)*ISNUMBER($H$11:$H$20)*($E$11:$E$20<E17))+SUMPRODUCT(ISNUMBER($E$11:$E$20)*($E$11:$E$20>0)*ISNUMBER($H$11:$H$20)*($E$11:$E$20=E17)*(ROW($E$11:$E$20)<ROW(E17))),"")
A18: 8 | D18: =IF(C18="","",IFERROR(INDEX(Taxas!$B$5:$B$13,MATCH(C18,Taxas!$A$5:$A$13,0)),"")) | F18: =IF(C18="","",IFERROR(IF(INDEX(Taxas!$D$5:$D$13,MATCH(C18,Taxas!$A$5:$A$13,0))="","",INDEX(Taxas!$D$5:$D$13,MATCH(C18,Taxas!$A$5:$A$13,0))),"")) | H18: =IF(ISNUMBER(G18),IF(G18>1,G18/100,G18),F18) | J18: =IF(AND(ISNUMBER(E18),E18>0,ISNUMBER(H18)),E18*H18,"") | K18: =IF(AND(ISNUMBER(J18),ISNUMBER(I18)),I18-J18,"") | L18: =IF(NOT(ISNUMBER(E18)),"",IF(E18<=0,"FASE VENCIDA",IF(NOT(ISNUMBER(H18)),"Falta a taxa",IF(NOT(ISNUMBER(I18)),"Falta o mínimo",IF(ROUND(I18,2)<ROUND(J18,2),"CRESCENDO: o mínimo não cobre o ataque",IF(ROUND(I18,2)=ROUND(J18,2),"Parado: o mínimo só paga os juros","Perdendo vida")))))) | M18: =IF(AND(ISNUMBER(E18),E18>0,ISNUMBER(H18)),1+SUMPRODUCT(ISNUMBER($E$11:$E$20)*($E$11:$E$20>0)*ISNUMBER($H$11:$H$20)*($H$11:$H$20>H18))+SUMPRODUCT(ISNUMBER($E$11:$E$20)*($E$11:$E$20>0)*ISNUMBER($H$11:$H$20)*($H$11:$H$20=H18)*(ROW($H$11:$H$20)<ROW(H18))),"") | N18: =IF(AND(ISNUMBER(E18),E18>0,ISNUMBER(H18)),1+SUMPRODUCT(ISNUMBER($E$11:$E$20)*($E$11:$E$20>0)*ISNUMBER($H$11:$H$20)*($E$11:$E$20<E18))+SUMPRODUCT(ISNUMBER($E$11:$E$20)*($E$11:$E$20>0)*ISNUMBER($H$11:$H$20)*($E$11:$E$20=E18)*(ROW($E$11:$E$20)<ROW(E18))),"")
A19: 9 | D19: =IF(C19="","",IFERROR(INDEX(Taxas!$B$5:$B$13,MATCH(C19,Taxas!$A$5:$A$13,0)),"")) | F19: =IF(C19="","",IFERROR(IF(INDEX(Taxas!$D$5:$D$13,MATCH(C19,Taxas!$A$5:$A$13,0))="","",INDEX(Taxas!$D$5:$D$13,MATCH(C19,Taxas!$A$5:$A$13,0))),"")) | H19: =IF(ISNUMBER(G19),IF(G19>1,G19/100,G19),F19) | J19: =IF(AND(ISNUMBER(E19),E19>0,ISNUMBER(H19)),E19*H19,"") | K19: =IF(AND(ISNUMBER(J19),ISNUMBER(I19)),I19-J19,"") | L19: =IF(NOT(ISNUMBER(E19)),"",IF(E19<=0,"FASE VENCIDA",IF(NOT(ISNUMBER(H19)),"Falta a taxa",IF(NOT(ISNUMBER(I19)),"Falta o mínimo",IF(ROUND(I19,2)<ROUND(J19,2),"CRESCENDO: o mínimo não cobre o ataque",IF(ROUND(I19,2)=ROUND(J19,2),"Parado: o mínimo só paga os juros","Perdendo vida")))))) | M19: =IF(AND(ISNUMBER(E19),E19>0,ISNUMBER(H19)),1+SUMPRODUCT(ISNUMBER($E$11:$E$20)*($E$11:$E$20>0)*ISNUMBER($H$11:$H$20)*($H$11:$H$20>H19))+SUMPRODUCT(ISNUMBER($E$11:$E$20)*($E$11:$E$20>0)*ISNUMBER($H$11:$H$20)*($H$11:$H$20=H19)*(ROW($H$11:$H$20)<ROW(H19))),"") | N19: =IF(AND(ISNUMBER(E19),E19>0,ISNUMBER(H19)),1+SUMPRODUCT(ISNUMBER($E$11:$E$20)*($E$11:$E$20>0)*ISNUMBER($H$11:$H$20)*($E$11:$E$20<E19))+SUMPRODUCT(ISNUMBER($E$11:$E$20)*($E$11:$E$20>0)*ISNUMBER($H$11:$H$20)*($E$11:$E$20=E19)*(ROW($E$11:$E$20)<ROW(E19))),"")
A20: 10 | D20: =IF(C20="","",IFERROR(INDEX(Taxas!$B$5:$B$13,MATCH(C20,Taxas!$A$5:$A$13,0)),"")) | F20: =IF(C20="","",IFERROR(IF(INDEX(Taxas!$D$5:$D$13,MATCH(C20,Taxas!$A$5:$A$13,0))="","",INDEX(Taxas!$D$5:$D$13,MATCH(C20,Taxas!$A$5:$A$13,0))),"")) | H20: =IF(ISNUMBER(G20),IF(G20>1,G20/100,G20),F20) | J20: =IF(AND(ISNUMBER(E20),E20>0,ISNUMBER(H20)),E20*H20,"") | K20: =IF(AND(ISNUMBER(J20),ISNUMBER(I20)),I20-J20,"") | L20: =IF(NOT(ISNUMBER(E20)),"",IF(E20<=0,"FASE VENCIDA",IF(NOT(ISNUMBER(H20)),"Falta a taxa",IF(NOT(ISNUMBER(I20)),"Falta o mínimo",IF(ROUND(I20,2)<ROUND(J20,2),"CRESCENDO: o mínimo não cobre o ataque",IF(ROUND(I20,2)=ROUND(J20,2),"Parado: o mínimo só paga os juros","Perdendo vida")))))) | M20: =IF(AND(ISNUMBER(E20),E20>0,ISNUMBER(H20)),1+SUMPRODUCT(ISNUMBER($E$11:$E$20)*($E$11:$E$20>0)*ISNUMBER($H$11:$H$20)*($H$11:$H$20>H20))+SUMPRODUCT(ISNUMBER($E$11:$E$20)*($E$11:$E$20>0)*ISNUMBER($H$11:$H$20)*($H$11:$H$20=H20)*(ROW($H$11:$H$20)<ROW(H20))),"") | N20: =IF(AND(ISNUMBER(E20),E20>0,ISNUMBER(H20)),1+SUMPRODUCT(ISNUMBER($E$11:$E$20)*($E$11:$E$20>0)*ISNUMBER($H$11:$H$20)*($E$11:$E$20<E20))+SUMPRODUCT(ISNUMBER($E$11:$E$20)*($E$11:$E$20>0)*ISNUMBER($H$11:$H$20)*($E$11:$E$20=E20)*(ROW($E$11:$E$20)<ROW(E20))),"")
A21: TOTAL | E21: =SUM(E11:E20) | I21: =SUM(I11:I20) | J21: =SUM(J11:J20)
A23: ORDEM DE ATAQUE
A24: O primeiro da lista é o ALVO: paga o mínimo de todos e joga a sobra inteira nele. Quando ele cai, o próximo vira alvo.
A25: AVALANCHE · maior taxa primeiro (paga menos juros) | H25: BOLA DE NEVE · menor vida primeiro (vitória mais cedo)
A26: Ordem | B26: Dívida | C26: Chefão | E26: Vida | F26: Taxa | H26: Ordem | I26: Dívida | L26: Chefão | M26: Vida | N26: Taxa
A27: =IF(COUNT($M$11:$M$20)>=1,1,"") | B27: =IF($A27="","",IFERROR(INDEX($B$11:$B$20,MATCH($A27,$M$11:$M$20,0)),"")) | C27: =IF($A27="","",IFERROR(INDEX($D$11:$D$20,MATCH($A27,$M$11:$M$20,0)),"")) | E27: =IF($A27="","",IFERROR(INDEX($E$11:$E$20,MATCH($A27,$M$11:$M$20,0)),"")) | F27: =IF($A27="","",IFERROR(INDEX($H$11:$H$20,MATCH($A27,$M$11:$M$20,0)),"")) | G27: ← ALVO | H27: =IF(COUNT($N$11:$N$20)>=1,1,"") | I27: =IF($H27="","",IFERROR(INDEX($B$11:$B$20,MATCH($H27,$N$11:$N$20,0)),"")) | L27: =IF($H27="","",IFERROR(INDEX($D$11:$D$20,MATCH($H27,$N$11:$N$20,0)),"")) | M27: =IF($H27="","",IFERROR(INDEX($E$11:$E$20,MATCH($H27,$N$11:$N$20,0)),"")) | N27: =IF($H27="","",IFERROR(INDEX($H$11:$H$20,MATCH($H27,$N$11:$N$20,0)),""))
A28: =IF(COUNT($M$11:$M$20)>=2,2,"") | B28: =IF($A28="","",IFERROR(INDEX($B$11:$B$20,MATCH($A28,$M$11:$M$20,0)),"")) | C28: =IF($A28="","",IFERROR(INDEX($D$11:$D$20,MATCH($A28,$M$11:$M$20,0)),"")) | E28: =IF($A28="","",IFERROR(INDEX($E$11:$E$20,MATCH($A28,$M$11:$M$20,0)),"")) | F28: =IF($A28="","",IFERROR(INDEX($H$11:$H$20,MATCH($A28,$M$11:$M$20,0)),"")) | H28: =IF(COUNT($N$11:$N$20)>=2,2,"") | I28: =IF($H28="","",IFERROR(INDEX($B$11:$B$20,MATCH($H28,$N$11:$N$20,0)),"")) | L28: =IF($H28="","",IFERROR(INDEX($D$11:$D$20,MATCH($H28,$N$11:$N$20,0)),"")) | M28: =IF($H28="","",IFERROR(INDEX($E$11:$E$20,MATCH($H28,$N$11:$N$20,0)),"")) | N28: =IF($H28="","",IFERROR(INDEX($H$11:$H$20,MATCH($H28,$N$11:$N$20,0)),""))
A29: =IF(COUNT($M$11:$M$20)>=3,3,"") | B29: =IF($A29="","",IFERROR(INDEX($B$11:$B$20,MATCH($A29,$M$11:$M$20,0)),"")) | C29: =IF($A29="","",IFERROR(INDEX($D$11:$D$20,MATCH($A29,$M$11:$M$20,0)),"")) | E29: =IF($A29="","",IFERROR(INDEX($E$11:$E$20,MATCH($A29,$M$11:$M$20,0)),"")) | F29: =IF($A29="","",IFERROR(INDEX($H$11:$H$20,MATCH($A29,$M$11:$M$20,0)),"")) | H29: =IF(COUNT($N$11:$N$20)>=3,3,"") | I29: =IF($H29="","",IFERROR(INDEX($B$11:$B$20,MATCH($H29,$N$11:$N$20,0)),"")) | L29: =IF($H29="","",IFERROR(INDEX($D$11:$D$20,MATCH($H29,$N$11:$N$20,0)),"")) | M29: =IF($H29="","",IFERROR(INDEX($E$11:$E$20,MATCH($H29,$N$11:$N$20,0)),"")) | N29: =IF($H29="","",IFERROR(INDEX($H$11:$H$20,MATCH($H29,$N$11:$N$20,0)),""))
A30: =IF(COUNT($M$11:$M$20)>=4,4,"") | B30: =IF($A30="","",IFERROR(INDEX($B$11:$B$20,MATCH($A30,$M$11:$M$20,0)),"")) | C30: =IF($A30="","",IFERROR(INDEX($D$11:$D$20,MATCH($A30,$M$11:$M$20,0)),"")) | E30: =IF($A30="","",IFERROR(INDEX($E$11:$E$20,MATCH($A30,$M$11:$M$20,0)),"")) | F30: =IF($A30="","",IFERROR(INDEX($H$11:$H$20,MATCH($A30,$M$11:$M$20,0)),"")) | H30: =IF(COUNT($N$11:$N$20)>=4,4,"") | I30: =IF($H30="","",IFERROR(INDEX($B$11:$B$20,MATCH($H30,$N$11:$N$20,0)),"")) | L30: =IF($H30="","",IFERROR(INDEX($D$11:$D$20,MATCH($H30,$N$11:$N$20,0)),"")) | M30: =IF($H30="","",IFERROR(INDEX($E$11:$E$20,MATCH($H30,$N$11:$N$20,0)),"")) | N30: =IF($H30="","",IFERROR(INDEX($H$11:$H$20,MATCH($H30,$N$11:$N$20,0)),""))
A31: =IF(COUNT($M$11:$M$20)>=5,5,"") | B31: =IF($A31="","",IFERROR(INDEX($B$11:$B$20,MATCH($A31,$M$11:$M$20,0)),"")) | C31: =IF($A31="","",IFERROR(INDEX($D$11:$D$20,MATCH($A31,$M$11:$M$20,0)),"")) | E31: =IF($A31="","",IFERROR(INDEX($E$11:$E$20,MATCH($A31,$M$11:$M$20,0)),"")) | F31: =IF($A31="","",IFERROR(INDEX($H$11:$H$20,MATCH($A31,$M$11:$M$20,0)),"")) | H31: =IF(COUNT($N$11:$N$20)>=5,5,"") | I31: =IF($H31="","",IFERROR(INDEX($B$11:$B$20,MATCH($H31,$N$11:$N$20,0)),"")) | L31: =IF($H31="","",IFERROR(INDEX($D$11:$D$20,MATCH($H31,$N$11:$N$20,0)),"")) | M31: =IF($H31="","",IFERROR(INDEX($E$11:$E$20,MATCH($H31,$N$11:$N$20,0)),"")) | N31: =IF($H31="","",IFERROR(INDEX($H$11:$H$20,MATCH($H31,$N$11:$N$20,0)),""))
A32: =IF(COUNT($M$11:$M$20)>=6,6,"") | B32: =IF($A32="","",IFERROR(INDEX($B$11:$B$20,MATCH($A32,$M$11:$M$20,0)),"")) | C32: =IF($A32="","",IFERROR(INDEX($D$11:$D$20,MATCH($A32,$M$11:$M$20,0)),"")) | E32: =IF($A32="","",IFERROR(INDEX($E$11:$E$20,MATCH($A32,$M$11:$M$20,0)),"")) | F32: =IF($A32="","",IFERROR(INDEX($H$11:$H$20,MATCH($A32,$M$11:$M$20,0)),"")) | H32: =IF(COUNT($N$11:$N$20)>=6,6,"") | I32: =IF($H32="","",IFERROR(INDEX($B$11:$B$20,MATCH($H32,$N$11:$N$20,0)),"")) | L32: =IF($H32="","",IFERROR(INDEX($D$11:$D$20,MATCH($H32,$N$11:$N$20,0)),"")) | M32: =IF($H32="","",IFERROR(INDEX($E$11:$E$20,MATCH($H32,$N$11:$N$20,0)),"")) | N32: =IF($H32="","",IFERROR(INDEX($H$11:$H$20,MATCH($H32,$N$11:$N$20,0)),""))
A33: =IF(COUNT($M$11:$M$20)>=7,7,"") | B33: =IF($A33="","",IFERROR(INDEX($B$11:$B$20,MATCH($A33,$M$11:$M$20,0)),"")) | C33: =IF($A33="","",IFERROR(INDEX($D$11:$D$20,MATCH($A33,$M$11:$M$20,0)),"")) | E33: =IF($A33="","",IFERROR(INDEX($E$11:$E$20,MATCH($A33,$M$11:$M$20,0)),"")) | F33: =IF($A33="","",IFERROR(INDEX($H$11:$H$20,MATCH($A33,$M$11:$M$20,0)),"")) | H33: =IF(COUNT($N$11:$N$20)>=7,7,"") | I33: =IF($H33="","",IFERROR(INDEX($B$11:$B$20,MATCH($H33,$N$11:$N$20,0)),"")) | L33: =IF($H33="","",IFERROR(INDEX($D$11:$D$20,MATCH($H33,$N$11:$N$20,0)),"")) | M33: =IF($H33="","",IFERROR(INDEX($E$11:$E$20,MATCH($H33,$N$11:$N$20,0)),"")) | N33: =IF($H33="","",IFERROR(INDEX($H$11:$H$20,MATCH($H33,$N$11:$N$20,0)),""))
A34: =IF(COUNT($M$11:$M$20)>=8,8,"") | B34: =IF($A34="","",IFERROR(INDEX($B$11:$B$20,MATCH($A34,$M$11:$M$20,0)),"")) | C34: =IF($A34="","",IFERROR(INDEX($D$11:$D$20,MATCH($A34,$M$11:$M$20,0)),"")) | E34: =IF($A34="","",IFERROR(INDEX($E$11:$E$20,MATCH($A34,$M$11:$M$20,0)),"")) | F34: =IF($A34="","",IFERROR(INDEX($H$11:$H$20,MATCH($A34,$M$11:$M$20,0)),"")) | H34: =IF(COUNT($N$11:$N$20)>=8,8,"") | I34: =IF($H34="","",IFERROR(INDEX($B$11:$B$20,MATCH($H34,$N$11:$N$20,0)),"")) | L34: =IF($H34="","",IFERROR(INDEX($D$11:$D$20,MATCH($H34,$N$11:$N$20,0)),"")) | M34: =IF($H34="","",IFERROR(INDEX($E$11:$E$20,MATCH($H34,$N$11:$N$20,0)),"")) | N34: =IF($H34="","",IFERROR(INDEX($H$11:$H$20,MATCH($H34,$N$11:$N$20,0)),""))
A35: =IF(COUNT($M$11:$M$20)>=9,9,"") | B35: =IF($A35="","",IFERROR(INDEX($B$11:$B$20,MATCH($A35,$M$11:$M$20,0)),"")) | C35: =IF($A35="","",IFERROR(INDEX($D$11:$D$20,MATCH($A35,$M$11:$M$20,0)),"")) | E35: =IF($A35="","",IFERROR(INDEX($E$11:$E$20,MATCH($A35,$M$11:$M$20,0)),"")) | F35: =IF($A35="","",IFERROR(INDEX($H$11:$H$20,MATCH($A35,$M$11:$M$20,0)),"")) | H35: =IF(COUNT($N$11:$N$20)>=9,9,"") | I35: =IF($H35="","",IFERROR(INDEX($B$11:$B$20,MATCH($H35,$N$11:$N$20,0)),"")) | L35: =IF($H35="","",IFERROR(INDEX($D$11:$D$20,MATCH($H35,$N$11:$N$20,0)),"")) | M35: =IF($H35="","",IFERROR(INDEX($E$11:$E$20,MATCH($H35,$N$11:$N$20,0)),"")) | N35: =IF($H35="","",IFERROR(INDEX($H$11:$H$20,MATCH($H35,$N$11:$N$20,0)),""))
A36: =IF(COUNT($M$11:$M$20)>=10,10,"") | B36: =IF($A36="","",IFERROR(INDEX($B$11:$B$20,MATCH($A36,$M$11:$M$20,0)),"")) | C36: =IF($A36="","",IFERROR(INDEX($D$11:$D$20,MATCH($A36,$M$11:$M$20,0)),"")) | E36: =IF($A36="","",IFERROR(INDEX($E$11:$E$20,MATCH($A36,$M$11:$M$20,0)),"")) | F36: =IF($A36="","",IFERROR(INDEX($H$11:$H$20,MATCH($A36,$M$11:$M$20,0)),"")) | H36: =IF(COUNT($N$11:$N$20)>=10,10,"") | I36: =IF($H36="","",IFERROR(INDEX($B$11:$B$20,MATCH($H36,$N$11:$N$20,0)),"")) | L36: =IF($H36="","",IFERROR(INDEX($D$11:$D$20,MATCH($H36,$N$11:$N$20,0)),"")) | M36: =IF($H36="","",IFERROR(INDEX($E$11:$E$20,MATCH($H36,$N$11:$N$20,0)),"")) | N36: =IF($H36="","",IFERROR(INDEX($H$11:$H$20,MATCH($H36,$N$11:$N$20,0)),""))
A38: Avalanche paga menos juros no total. Bola de Neve dá a primeira vitória mais cedo. Se você desanima fácil, vá de Bola de Neve; se aguenta esperar, Avalanche. As duas são muito melhores que pagar só o mínimo.
A40: Educativo: não é recomendação de investimento, não promete resultado e não substitui orientação profissional. Taxas médias do Banco Central de setembro de 2026 (consignado CLT: média de agosto de 2026). Confira sempre o contrato e o CET da sua dívida.

Sheet Placar mensal
A1: PLACAR MENSAL
A2: Din: todo mês, anote o que pagou em cada chefão e a vida que ficou (está no app ou na fatura). A barra de vida total tem que cair.
A3: VIDA NO INÍCIO | D3: VIDA HOJE | G3: VIDA DERROTADA | J3: TOTAL QUE VOCÊ PAGOU | M3: ATAQUE QUE VOCÊ TOMOU
A4: =IF(ISNUMBER(X8),X8,"") | D4: =IF(COUNT(X8:X32)=0,"",INDEX(X8:X32,COUNT(X8:X32))) | G4: =IF(OR(A4="",D4="",A4=0),"",1-D4/A4) | J4: =SUM(W9:W32) | M4: =SUM(Y9:Y32) | P4: =IF(G4="","",REPT("█",MAX(0,ROUND(G4*20,0)))&REPT("░",20-MAX(0,MIN(20,ROUND(G4*20,0)))))
A6: Mês | B6: Data | C6: =IF('Meus chefões'!B11="","Chefão 1",'Meus chefões'!B11) | E6: =IF('Meus chefões'!B12="","Chefão 2",'Meus chefões'!B12) | G6: =IF('Meus chefões'!B13="","Chefão 3",'Meus chefões'!B13) | I6: =IF('Meus chefões'!B14="","Chefão 4",'Meus chefões'!B14) | K6: =IF('Meus chefões'!B15="","Chefão 5",'Meus chefões'!B15) | M6: =IF('Meus chefões'!B16="","Chefão 6",'Meus chefões'!B16) | O6: =IF('Meus chefões'!B17="","Chefão 7",'Meus chefões'!B17) | Q6: =IF('Meus chefões'!B18="","Chefão 8",'Meus chefões'!B18) | S6: =IF('Meus chefões'!B19="","Chefão 9",'Meus chefões'!B19) | U6: =IF('Meus chefões'!B20="","Chefão 10",'Meus chefões'!B20) | W6: Total pago | X6: VIDA TOTAL | Y6: Ataque que você tomou | Z6: Vida derrotada | AA6: Barra
C7: Pagou | D7: Vida que ficou | E7: Pagou | F7: Vida que ficou | G7: Pagou | H7: Vida que ficou | I7: Pagou | J7: Vida que ficou | K7: Pagou | L7: Vida que ficou | M7: Pagou | N7: Vida que ficou | O7: Pagou | P7: Vida que ficou | Q7: Pagou | R7: Vida que ficou | S7: Pagou | T7: Vida que ficou | U7: Pagou | V7: Vida que ficou
A8: Início | B8: EXEMPLO | C8: — | D8: 2000 | E8: — | F8: 800 | G8: — | H8: 3000 | I8: — | K8: — | M8: — | O8: — | Q8: — | S8: — | U8: — | W8: — | X8: =IF(COUNT(D8,F8,H8,J8,L8,N8,P8,R8,T8,V8)=0,"",SUM(D8,F8,H8,J8,L8,N8,P8,R8,T8,V8)) | Y8: — | Z8: =IF(AND(ISNUMBER(X8),ISNUMBER(X$8),X$8>0),1-X8/X$8,"") | AA8: =IF(ISNUMBER(Z8),REPT("█",MAX(0,MIN(20,ROUND(Z8*20,0)))),"")
A9: Mês 1 | B9: EXEMPLO | C9: 400 | D9: 1787.44 | E9: 50 | F9: 810.25 | G9: 150 | H9: 3042.48 | W9: =IF(COUNT(C9,E9,G9,I9,K9,M9,O9,Q9,S9,U9)=0,"",SUM(C9,E9,G9,I9,K9,M9,O9,Q9,S9,U9)) | X9: =IF(COUNT(D9,F9,H9,J9,L9,N9,P9,R9,T9,V9)=0,"",SUM(D9,F9,H9,J9,L9,N9,P9,R9,T9,V9)) | Y9: =IF(AND(ISNUMBER(X9),ISNUMBER(X8)),X9-X8+N(W9),"") | Z9: =IF(AND(ISNUMBER(X9),ISNUMBER(X$8),X$8>0),1-X9/X$8,"") | AA9: =IF(ISNUMBER(Z9),REPT("█",MAX(0,MIN(20,ROUND(Z9*20,0)))),"")
A10: Mês 2 | B10: EXEMPLO | C10: 400 | D10: 1554.95 | E10: 50 | F10: 821.27 | G10: 150 | H10: 3087.68 | W10: =IF(COUNT(C10,E10,G10,I10,K10,M10,O10,Q10,S10,U10)=0,"",SUM(C10,E10,G10,I10,K10,M10,O10,Q10,S10,U10)) | X10: =IF(COUNT(D10,F10,H10,J10,L10,N10,P10,R10,T10,V10)=0,"",SUM(D10,F10,H10,J10,L10,N10,P10,R10,T10,V10)) | Y10: =IF(AND(ISNUMBER(X10),ISNUMBER(X9)),X10-X9+N(W10),"") | Z10: =IF(AND(ISNUMBER(X10),ISNUMBER(X$8),X$8>0),1-X10/X$8,"") | AA10: =IF(ISNUMBER(Z10),REPT("█",MAX(0,MIN(20,ROUND(Z10*20,0)))),"")
A11: Mês 3 | W11: =IF(COUNT(C11,E11,G11,I11,K11,M11,O11,Q11,S11,U11)=0,"",SUM(C11,E11,G11,I11,K11,M11,O11,Q11,S11,U11)) | X11: =IF(COUNT(D11,F11,H11,J11,L11,N11,P11,R11,T11,V11)=0,"",SUM(D11,F11,H11,J11,L11,N11,P11,R11,T11,V11)) | Y11: =IF(AND(ISNUMBER(X11),ISNUMBER(X10)),X11-X10+N(W11),"") | Z11: =IF(AND(ISNUMBER(X11),ISNUMBER(X$8),X$8>0),1-X11/X$8,"") | AA11: =IF(ISNUMBER(Z11),REPT("█",MAX(0,MIN(20,ROUND(Z11*20,0)))),"")
A12: Mês 4 | W12: =IF(COUNT(C12,E12,G12,I12,K12,M12,O12,Q12,S12,U12)=0,"",SUM(C12,E12,G12,I12,K12,M12,O12,Q12,S12,U12)) | X12: =IF(COUNT(D12,F12,H12,J12,L12,N12,P12,R12,T12,V12)=0,"",SUM(D12,F12,H12,J12,L12,N12,P12,R12,T12,V12)) | Y12: =IF(AND(ISNUMBER(X12),ISNUMBER(X11)),X12-X11+N(W12),"") | Z12: =IF(AND(ISNUMBER(X12),ISNUMBER(X$8),X$8>0),1-X12/X$8,"") | AA12: =IF(ISNUMBER(Z12),REPT("█",MAX(0,MIN(20,ROUND(Z12*20,0)))),"")
A13: Mês 5 | W13: =IF(COUNT(C13,E13,G13,I13,K13,M13,O13,Q13,S13,U13)=0,"",SUM(C13,E13,G13,I13,K13,M13,O13,Q13,S13,U13)) | X13: =IF(COUNT(D13,F13,H13,J13,L13,N13,P13,R13,T13,V13)=0,"",SUM(D13,F13,H13,J13,L13,N13,P13,R13,T13,V13)) | Y13: =IF(AND(ISNUMBER(X13),ISNUMBER(X12)),X13-X12+N(W13),"") | Z13: =IF(AND(ISNUMBER(X13),ISNUMBER(X$8),X$8>0),1-X13/X$8,"") | AA13: =IF(ISNUMBER(Z13),REPT("█",MAX(0,MIN(20,ROUND(Z13*20,0)))),"")
A14: Mês 6 | W14: =IF(COUNT(C14,E14,G14,I14,K14,M14,O14,Q14,S14,U14)=0,"",SUM(C14,E14,G14,I14,K14,M14,O14,Q14,S14,U14)) | X14: =IF(COUNT(D14,F14,H14,J14,L14,N14,P14,R14,T14,V14)=0,"",SUM(D14,F14,H14,J14,L14,N14,P14,R14,T14,V14)) | Y14: =IF(AND(ISNUMBER(X14),ISNUMBER(X13)),X14-X13+N(W14),"") | Z14: =IF(AND(ISNUMBER(X14),ISNUMBER(X$8),X$8>0),1-X14/X$8,"") | AA14: =IF(ISNUMBER(Z14),REPT("█",MAX(0,MIN(20,ROUND(Z14*20,0)))),"")
A15: Mês 7 | W15: =IF(COUNT(C15,E15,G15,I15,K15,M15,O15,Q15,S15,U15)=0,"",SUM(C15,E15,G15,I15,K15,M15,O15,Q15,S15,U15)) | X15: =IF(COUNT(D15,F15,H15,J15,L15,N15,P15,R15,T15,V15)=0,"",SUM(D15,F15,H15,J15,L15,N15,P15,R15,T15,V15)) | Y15: =IF(AND(ISNUMBER(X15),ISNUMBER(X14)),X15-X14+N(W15),"") | Z15: =IF(AND(ISNUMBER(X15),ISNUMBER(X$8),X$8>0),1-X15/X$8,"") | AA15: =IF(ISNUMBER(Z15),REPT("█",MAX(0,MIN(20,ROUND(Z15*20,0)))),"")
A16: Mês 8 | W16: =IF(COUNT(C16,E16,G16,I16,K16,M16,O16,Q16,S16,U16)=0,"",SUM(C16,E16,G16,I16,K16,M16,O16,Q16,S16,U16)) | X16: =IF(COUNT(D16,F16,H16,J16,L16,N16,P16,R16,T16,V16)=0,"",SUM(D16,F16,H16,J16,L16,N16,P16,R16,T16,V16)) | Y16: =IF(AND(ISNUMBER(X16),ISNUMBER(X15)),X16-X15+N(W16),"") | Z16: =IF(AND(ISNUMBER(X16),ISNUMBER(X$8),X$8>0),1-X16/X$8,"") | AA16: =IF(ISNUMBER(Z16),REPT("█",MAX(0,MIN(20,ROUND(Z16*20,0)))),"")
A17: Mês 9 | W17: =IF(COUNT(C17,E17,G17,I17,K17,M17,O17,Q17,S17,U17)=0,"",SUM(C17,E17,G17,I17,K17,M17,O17,Q17,S17,U17)) | X17: =IF(COUNT(D17,F17,H17,J17,L17,N17,P17,R17,T17,V17)=0,"",SUM(D17,F17,H17,J17,L17,N17,P17,R17,T17,V17)) | Y17: =IF(AND(ISNUMBER(X17),ISNUMBER(X16)),X17-X16+N(W17),"") | Z17: =IF(AND(ISNUMBER(X17),ISNUMBER(X$8),X$8>0),1-X17/X$8,"") | AA17: =IF(ISNUMBER(Z17),REPT("█",MAX(0,MIN(20,ROUND(Z17*20,0)))),"")
A18: Mês 10 | W18: =IF(COUNT(C18,E18,G18,I18,K18,M18,O18,Q18,S18,U18)=0,"",SUM(C18,E18,G18,I18,K18,M18,O18,Q18,S18,U18)) | X18: =IF(COUNT(D18,F18,H18,J18,L18,N18,P18,R18,T18,V18)=0,"",SUM(D18,F18,H18,J18,L18,N18,P18,R18,T18,V18)) | Y18: =IF(AND(ISNUMBER(X18),ISNUMBER(X17)),X18-X17+N(W18),"") | Z18: =IF(AND(ISNUMBER(X18),ISNUMBER(X$8),X$8>0),1-X18/X$8,"") | AA18: =IF(ISNUMBER(Z18),REPT("█",MAX(0,MIN(20,ROUND(Z18*20,0)))),"")
A19: Mês 11 | W19: =IF(COUNT(C19,E19,G19,I19,K19,M19,O19,Q19,S19,U19)=0,"",SUM(C19,E19,G19,I19,K19,M19,O19,Q19,S19,U19)) | X19: =IF(COUNT(D19,F19,H19,J19,L19,N19,P19,R19,T19,V19)=0,"",SUM(D19,F19,H19,J19,L19,N19,P19,R19,T19,V19)) | Y19: =IF(AND(ISNUMBER(X19),ISNUMBER(X18)),X19-X18+N(W19),"") | Z19: =IF(AND(ISNUMBER(X19),ISNUMBER(X$8),X$8>0),1-X19/X$8,"") | AA19: =IF(ISNUMBER(Z19),REPT("█",MAX(0,MIN(20,ROUND(Z19*20,0)))),"")
A20: Mês 12 | W20: =IF(COUNT(C20,E20,G20,I20,K20,M20,O20,Q20,S20,U20)=0,"",SUM(C20,E20,G20,I20,K20,M20,O20,Q20,S20,U20)) | X20: =IF(COUNT(D20,F20,H20,J20,L20,N20,P20,R20,T20,V20)=0,"",SUM(D20,F20,H20,J20,L20,N20,P20,R20,T20,V20)) | Y20: =IF(AND(ISNUMBER(X20),ISNUMBER(X19)),X20-X19+N(W20),"") | Z20: =IF(AND(ISNUMBER(X20),ISNUMBER(X$8),X$8>0),1-X20/X$8,"") | AA20: =IF(ISNUMBER(Z20),REPT("█",MAX(0,MIN(20,ROUND(Z20*20,0)))),"")
A21: Mês 13 | W21: =IF(COUNT(C21,E21,G21,I21,K21,M21,O21,Q21,S21,U21)=0,"",SUM(C21,E21,G21,I21,K21,M21,O21,Q21,S21,U21)) | X21: =IF(COUNT(D21,F21,H21,J21,L21,N21,P21,R21,T21,V21)=0,"",SUM(D21,F21,H21,J21,L21,N21,P21,R21,T21,V21)) | Y21: =IF(AND(ISNUMBER(X21),ISNUMBER(X20)),X21-X20+N(W21),"") | Z21: =IF(AND(ISNUMBER(X21),ISNUMBER(X$8),X$8>0),1-X21/X$8,"") | AA21: =IF(ISNUMBER(Z21),REPT("█",MAX(0,MIN(20,ROUND(Z21*20,0)))),"")
A22: Mês 14 | W22: =IF(COUNT(C22,E22,G22,I22,K22,M22,O22,Q22,S22,U22)=0,"",SUM(C22,E22,G22,I22,K22,M22,O22,Q22,S22,U22)) | X22: =IF(COUNT(D22,F22,H22,J22,L22,N22,P22,R22,T22,V22)=0,"",SUM(D22,F22,H22,J22,L22,N22,P22,R22,T22,V22)) | Y22: =IF(AND(ISNUMBER(X22),ISNUMBER(X21)),X22-X21+N(W22),"") | Z22: =IF(AND(ISNUMBER(X22),ISNUMBER(X$8),X$8>0),1-X22/X$8,"") | AA22: =IF(ISNUMBER(Z22),REPT("█",MAX(0,MIN(20,ROUND(Z22*20,0)))),"")
... A32: Mês 24 | W32: =IF(COUNT(C32,E32,G32,I32,K32,M32,O32,Q32,S32,U32)=0,"",SUM(C32,E32,G32,I32,K32,M32,O32,Q32,S32,U32)) | X32: =IF(COUNT(D32,F32,H32,J32,L32,N32,P32,R32,T32,V32)=0,"",SUM(D32,F32,H32,J32,L32,N32,P32,R32,T32,V32)) | Y32: =IF(AND(ISNUMBER(X32),ISNUMBER(X31)),X32-X31+N(W32),"") | Z32: =IF(AND(ISNUMBER(X32),ISNUMBER(X$8),X$8>0),1-X32/X$8,"") | AA32: =IF(ISNUMBER(Z32),REPT("█",MAX(0,MIN(20,ROUND(Z32*20,0)))),"")
A34: Linha "Início": a vida de cada chefão no dia em que você começou (copie da aba Meus chefões). As linhas EXEMPLO são a Avalanche da Ana nos 2 primeiros meses, feitas pelas contas do livro: apague e coloque as suas. "Ataque que você tomou" = vida de agora − vida do mês anterior + o que você pagou, ou seja, os juros (e multas) que entraram no mês.
A55: Educativo: não é recomendação de investimento, não promete resultado e não substitui orientação profissional. Taxas médias do Banco Central de setembro de 2026 (consignado CLT: média de agosto de 2026). Confira sempre o contrato e o CET da sua dívida.

Sheet Plano de 90 dias
A1: MISSÃO FINAL: 90 DIAS
A2: Din: doze semanas, uma missão por semana. Terminou? Escolha "Feito" na última coluna.
A4: MISSÕES FEITAS
A5: =COUNTIF(D7:D18,"Feito")&" de 12" | C5: =REPT("█",COUNTIF(D7:D18,"Feito"))&REPT("░",12-COUNTIF(D7:D18,"Feito")) | D5: =IF(COUNTIF(D7:D18,"Feito")=12,"MUNDO 1 VENCIDO!","")
A6: Semana | B6: Missão | C6: O que fazer | D6: Feito?
A7: Semana 1 | B7: Mapa do jogo | C7: Puxe o Registrato, as faturas e os extratos. Preencha uma ficha por dívida.
A8: Semana 2 | B8: Placar | C8: Some a vida total e o ataque do mês. Liste o essencial e descubra quanto sobra.
A9: Semana 3 | B9: Estratégia | C9: Escolha Avalanche ou Bola de Neve e defina o primeiro alvo.
A10: Semana 4 | B10: Feche as portas | C10: Reduza o limite do cheque especial e do cartão. Tire os cartões salvos dos apps.
A11: Semana 5 | B11: Renegociar | C11: Ligue para os credores das dívidas atrasadas. Peça tudo por escrito.
A12: Semana 6 | B12: Comparar | C12: Simule portabilidade e troca por dívida mais barata. Compare taxa ao mês e CET.
A13: Semana 7 | B13: Decidir | C13: Feche só os acordos que cabem no bolso. Atualize as fichas.
A14: Semana 8 | B14: Gastos invisíveis | C14: Corte três gastos e mande a economia para o alvo.
A15: Semana 9 | B15: Escudo | C15: Comece a reserva de emergência, nem que seja com R$ 50.
A16: Semana 10 | B16: Placar de novo | C16: Atualize as fichas. A vida total caiu? O ataque do mês caiu?
A17: Semana 11 | B17: Ajuste | C17: Se algum chefão está crescendo, volte à Fase 4. Se tudo cai, mantenha o ritmo.
A18: Semana 12 | B18: Próximo alvo | C18: Comemore cada fase vencida e escreva o plano dos próximos 90 dias.
A20: Quando o último chefão cai, o dinheiro que ia para as dívidas continua chegando todo mês. Agora ele é seu: é o Mundo 2, O Cofre.
A22: Educativo: não é recomendação de investimento, não promete resultado e não substitui orientação profissional. Taxas médias do Banco Central de setembro de 2026 (consignado CLT: média de agosto de 2026). Confira sempre o contrato e o CET da sua dívida.

Sheet Taxas
A1: TAXAS MÉDIAS DOS CHEFÕES
A2: Banco Central do Brasil, taxas médias de setembro de 2026 (divulgadas em 29/10/2026). Taxa ao mês = (1 + taxa ao ano)^(1/12) − 1, a mesma conta do livro.
A4: Tipo de dívida | B4: Chefão do livro | C4: Taxa ao ano | D4: Taxa ao mês | E4: Fonte
A5: Rotativo do cartão | B5: Dragão do Rotativo | C5: 4.517 | D5: =(1+C5)^(1/12)-1 | E5: BC, set/2026
A6: Parcelamento da fatura | B6: Golem do Parcelado | C6: 1.93 | D6: =(1+C6)^(1/12)-1 | E6: BC, set/2026
A7: Cheque especial | B7: Sombra do Cheque Especial | C7: 1.39 | D7: =(1+C7)^(1/12)-1 | E7: BC, set/2026
A8: Crédito pessoal | B8: Cavaleiro do Crédito Pessoal | C8: 1.109 | D8: =(1+C8)^(1/12)-1 | E8: BC, set/2026
A9: Consignado privado (CLT) | B9: Ogro do Consignado CLT | C9: 0.5634 | D9: =(1+C9)^(1/12)-1 | E9: BC, média de ago/2026 (série 20744)
A10: Consignado | B10: Lacaio do Consignado | C10: 0.285 | D10: =(1+C10)^(1/12)-1 | E10: BC, set/2026
A11: Financiamento de veículos | B11: Tartaruga do Financiamento | C11: 0.262 | D11: =(1+C11)^(1/12)-1 | E11: BC, set/2026
A12: Contas atrasadas (luz/água/telefone) | B12: Goblin das Contas Atrasadas | C12: =(1+D12)^12-1 | D12: 0.01 | E12: Juros de mora de 1% a.m. + multa de até 2% (ANEEL/concessionárias, via Procon-SP)
A13: Outra dívida | B13: Chefão sem ficha | E13: Sem média: digite a taxa do seu contrato em "Minha taxa"
A15: As taxas mudam todo mês. Atualize a coluna "Taxa ao ano" com a média nova do Banco Central (bcb.gov.br, estatísticas monetárias e de crédito), ou use a taxa do seu contrato em "Minha taxa".
A16: Educativo: não é recomendação de investimento, não promete resultado e não substitui orientação profissional. Taxas médias do Banco Central de setembro de 2026 (consignado CLT: média de agosto de 2026). Confira sempre o contrato e o CET da sua dívida.
